<?xml version="1.0" encoding="UTF-8"?>
<objects serializationModel="Studio.02.02.00">
	<object class="AudioFile" id="{b8e54abc-6d90-4740-86c4-07bdba7acd94}">
		<property name="assetPath">
			<value>k) Right Puzzle Room Success/01_Player_Page09_Line04.wav</value>
		</property>
		<property name="frequencyInKHz">
			<value>48</value>
		</property>
		<property name="channelCount">
			<value>2</value>
		</property>
		<property name="length">
			<value>3.2576458333333331</value>
		</property>
		<relationship name="masterAssetFolder">
			<destination>{bdf32436-090c-431f-9ceb-bb6d786bee55}</destination>
		</relationship>
	</object>
</objects>
